hijax/__init__.py
hijax/abstract_worker.py
hijax/setup/__init__.py
hijax/setup/setup_config.py
hijax/setup/setup_loaders.py
hijax/setup/setup_worker.py
hijax/setup/utils.py
hijax-0.1.0.dist-info/LICENSE
hijax-0.1.0.dist-info/WHEEL
hijax-0.1.0.dist-info/METADATA
hijax-0.1.0.dist-info/RECORD
